nomadicml/__init__.py
nomadicml/client.py
nomadicml/cloud_integrations.py
nomadicml/exceptions.py
nomadicml/test.py
nomadicml/types.py
nomadicml/utils.py
nomadicml/video.py
nomadicml-0.1.36.dist-info/licenses/LICENSE
tests/__init__.py
tests/test_client.py
tests/test_integration.py
tests/test_utils.py
tests/test_video.py
tests/upload_batch_dict_e2e.py
tests/upload_url_with_name_e2e.py
tests/upload_with_name_param_e2e.py
nomadicml-0.1.36.dist-info/METADATA
nomadicml-0.1.36.dist-info/WHEEL
nomadicml-0.1.36.dist-info/top_level.txt
nomadicml-0.1.36.dist-info/RECORD
